asterix4py/AsterixParser.py
asterix4py/__init__.py
asterix4py/icao6bitchars.py
asterix4py/config/__init__.py
asterix4py/config/asterix.dtd
asterix4py/config/asterix.ini
asterix4py/config/asterix_cat001_1_1.xml
asterix4py/config/asterix_cat002_1_0.xml
asterix4py/config/asterix_cat008_1_0.xml
asterix4py/config/asterix_cat010_1_1.xml
asterix4py/config/asterix_cat019_1_2.xml
asterix4py/config/asterix_cat020_1_7.xml
asterix4py/config/asterix_cat021_0_26.xml
asterix4py/config/asterix_cat021_1_4.xml
asterix4py/config/asterix_cat021_1_8.xml
asterix4py/config/asterix_cat021_2_2.xml
asterix4py/config/asterix_cat023_1_2.xml
asterix4py/config/asterix_cat030_6_2.xml
asterix4py/config/asterix_cat031_6_2.xml
asterix4py/config/asterix_cat032_6_2.xml
asterix4py/config/asterix_cat032_7_0.xml
asterix4py/config/asterix_cat034_1_26.xml
asterix4py/config/asterix_cat048_1_14.xml
asterix4py/config/asterix_cat062_0_17.xml
asterix4py/config/asterix_cat062_1_16.xml
asterix4py/config/asterix_cat062_1_18.xml
asterix4py/config/asterix_cat062_1_7.xml
asterix4py/config/asterix_cat062_1_9.xml
asterix4py/config/asterix_cat063_1_3.xml
asterix4py/config/asterix_cat065_1_2.xml
asterix4py/config/asterix_cat065_1_3.xml
asterix4py/config/asterix_cat242_1_0.xml
asterix4py/config/asterix_cat252_6_1.xml
asterix4py/config/asterix_cat252_6_2.xml
asterix4py/config/asterix_cat252_7_0.xml
asterix4py-1.0.6.dist-info/LICENSE
asterix4py-1.0.6.dist-info/METADATA
asterix4py-1.0.6.dist-info/WHEEL
asterix4py-1.0.6.dist-info/top_level.txt
asterix4py-1.0.6.dist-info/RECORD
