Metadata-Version: 2.1
Name: asterix4py
Version: 1.0.6
Summary: Pure python library for decoding Eurocontrol Asterix binary data
Home-page: https://github.com/filipjonckers/asterix4py
Author: Filip Jonckers
Author-email: 
License: MIT License
Project-URL: Bug Reports, https://github.com/filipjonckers/asterix4py/issues
Project-URL: Source, https://github.com/filipjonckers/asterix4py
Keywords: asterix radar artas eurocontrol mode-s
Platform: any
Classifier: Development Status :: 3 - Alpha
Classifier: Programming Language :: Python
Classifier: Programming Language :: Python :: 3
Classifier: Programming Language :: Python :: 3.7
Classifier: Programming Language :: Python :: 3.8
Classifier: Intended Audience :: Developers
Classifier: Intended Audience :: Information Technology
Classifier: Intended Audience :: Science/Research
Classifier: Operating System :: MacOS
Classifier: Operating System :: Microsoft :: Windows
Classifier: Operating System :: POSIX :: Linux
Classifier: License :: OSI Approved :: MIT License
Classifier: Topic :: Software Development
Classifier: Topic :: Software Development :: Libraries :: Python Modules
Classifier: Topic :: Scientific/Engineering
Classifier: Topic :: Scientific/Engineering :: Information Analysis
Classifier: Topic :: Scientific/Engineering :: Interface Engine/Protocol Translator
Requires-Python: >=3.7
